setup.cfg
setup.py
cabot_alert_ovh/__init__.py
cabot_alert_ovh/models.py
cabot_alert_ovh.egg-info/PKG-INFO
cabot_alert_ovh.egg-info/SOURCES.txt
cabot_alert_ovh.egg-info/dependency_links.txt
cabot_alert_ovh.egg-info/requires.txt
cabot_alert_ovh.egg-info/top_level.txt