Metadata-Version: 1.1
Name: cabot-alert-ovh
Version: 1.0.0b1
Summary: An Ovh alert plugin for Cabot by Arachnys
Home-page: http://cabotapp.com
Author: Rachid Zarouali
Author-email: rachid.zarouali@synolia.com
License: MIT
Keywords: cabot ovh monitoring
Platform: UNKNOWN
Classifier: Development Status :: 4 - Beta
Classifier: Intended Audience :: Developers
Classifier: Topic :: System :: Monitoring
Classifier: License :: OSI Approved :: MIT License
Classifier: Programming Language :: Python :: 2.7
